Swifter/__init__.py
Swifter/swifter.py
Swifter_in_NLP_Fake_News_Identification-0.0.1.dist-info/LICENSE
Swifter_in_NLP_Fake_News_Identification-0.0.1.dist-info/METADATA
Swifter_in_NLP_Fake_News_Identification-0.0.1.dist-info/WHEEL
Swifter_in_NLP_Fake_News_Identification-0.0.1.dist-info/top_level.txt
Swifter_in_NLP_Fake_News_Identification-0.0.1.dist-info/RECORD
