Metadata-Version: 2.1
Name: Swifter-in-NLP-Fake-News-Identification
Version: 0.0.1
Summary: UNKNOWN
Home-page: UNKNOWN
Author: Sagnik Sarkar
License: UNKNOWN
Keywords: python,NLP,News Paper,Fake News,NLP News
Platform: UNKNOWN
Classifier: Development Status :: 1 - Planning
Classifier: Intended Audience :: Developers
Classifier: Programming Language :: Python :: 3
Classifier: Operating System :: Unix
Classifier: Operating System :: MacOS :: MacOS X
Classifier: Operating System :: Microsoft :: Windows
Requires-Dist: GoogleNews
Requires-Dist: newspaper3k
Requires-Dist: pandas
Requires-Dist: nltk
